PyMoq-0.3.2.dist-info/METADATA
PyMoq-0.3.2.dist-info/RECORD
PyMoq-0.3.2.dist-info/WHEEL
PyMoq-0.3.2.dist-info/top_level.txt
pymoq/__init__.py
pymoq/handler.py
pymoq/pymoq.py
pymoq/stub/__init__.py
pymoq/stub/loader.py
pymoq/stub/matcher.py
pymoq/stub/request.py
pymoq/stub/verification.py
