Metadata-Version: 2.1
Name: PyMoq
Version: 0.3.2
Summary: An API mocking tool
Home-page: https://github.com/snifter/pymoq
Author: Marek Podsiadły
Author-email: marek@podsiadly.info
License: UNKNOWN
Keywords: api testing mocking
Platform: UNKNOWN
Classifier: License :: OSI Approved :: MIT License
Classifier: Programming Language :: Python :: 3.5
Classifier: Programming Language :: Python :: 3.6
Provides-Extra: test
Provides-Extra: test
Requires-Dist: requests; extra == 'test'
